SimConnect/Attributes.py
SimConnect/Constants.py
SimConnect/Enum.py
SimConnect/EventList.py
SimConnect/FacilitiesList.py
SimConnect/RequestList.py
SimConnect/SimConnect.dll
SimConnect/SimConnect.py
SimConnect/__init__.py
SimConnect-0.4.25.dist-info/LICENSE
SimConnect-0.4.25.dist-info/METADATA
SimConnect-0.4.25.dist-info/WHEEL
SimConnect-0.4.25.dist-info/top_level.txt
SimConnect-0.4.25.dist-info/RECORD
