Metadata-Version: 2.1
Name: SimConnect
Version: 0.4.25
Summary: Adds a pythonic wrapper for SimConnect SDK.
Home-page: https://github.com/odwdinc/Python-SimConnect
Author: Anthony Pray
Author-email: anthony.pray@gmail.com
Maintainer: Anthony Pray
Maintainer-email: anthony.pray@gmail.com
License: AGPL 3.0
Keywords: ctypes,FlightSim,SimConnect,Flight,Simulator
Platform: UNKNOWN
Classifier: Development Status :: 2 - Pre-Alpha
Classifier: Environment :: Console
Classifier: Intended Audience :: Developers
Classifier: License :: OSI Approved :: GNU Affero General Public License v3 or later (AGPLv3+)
Classifier: Operating System :: OS Independent
Classifier: Programming Language :: Python
Classifier: Programming Language :: Python :: 3
Classifier: Programming Language :: Python :: 3.6
Classifier: Programming Language :: Python :: 3.7
Classifier: Programming Language :: Python :: 3.8
Classifier: Programming Language :: Python :: Implementation :: CPython
Requires-Python: >=3.6
License-File: LICENSE
